MANIFEST.in
README.rst
setup.py
requests_raven/__init__.py
requests_raven/ebscohost.py
requests_raven/jstor.py
requests_raven/oxford_qje.py
requests_raven/raven.py
requests_raven/test.py
requests_raven/wiley.py
requests_raven.egg-info/PKG-INFO
requests_raven.egg-info/SOURCES.txt
requests_raven.egg-info/dependency_links.txt
requests_raven.egg-info/not-zip-safe
requests_raven.egg-info/requires.txt
requests_raven.egg-info/top_level.txt