Metadata-Version: 1.0
Name: requests-raven
Version: 0.0.1
Summary: Requests wrapper to log onto Raven (University of Cambridge).
Home-page: http://www.erinhengel.com/software/requests-raven/
Author: Erin Hengel
Author-email: erin.hengel@gmail.com
License: Apache 2.0
Platform: UNKNOWN
